<?xml version="1.0" encoding="utf-8" ?>
<dwsync>
<file name="banner1.jpg" server="mzalokostas.gr" local="129959316000000000" remote="129959316000000000" />
<file name="banner2.jpg" server="mzalokostas.gr" local="129959316000000000" remote="129959316000000000" />
<file name="banner3.jpg" server="mzalokostas.gr" local="129959316000000000" remote="129959316000000000" />
<file name="followup.swf" server="mzalokostas.gr" local="129959316000000000" remote="129959316000000000" />
<file name="logo_final.jpg" server="mzalokostas.gr" local="129959316000000000" remote="129959316000000000" />
<file name="teaser1.swf" server="mzalokostas.gr" local="129959316000000000" remote="129959316000000000" />
<file name="teaser2.swf" server="mzalokostas.gr" local="129959316000000000" remote="129959316000000000" />
<file name="banner1_thmb.jpg" server="mzalokostas.gr" local="130148424741835558" remote="130148176200000000" />
<file name="banner2_thmb.jpg" server="mzalokostas.gr" local="130148424749960683" remote="130148176200000000" />
<file name="banner3_thmb.jpg" server="mzalokostas.gr" local="130148424757648301" remote="130148176200000000" />
<file name="logo_final_thmb.jpg" server="mzalokostas.gr" local="130148424765323419" remote="130148176200000000" />
</dwsync>